manual/aws/get_ec2_ami.py
pulumi_easy/__init__.py
pulumi_easy/aws/__init__.py
pulumi_easy/aws/ec2/__init__.py
pulumi_easy/aws/ec2/ec2.py
pulumi_easy/aws/ec2/ec2_al.py
pulumi_easy/aws/ec2/ec2_ubuntu.py
pulumi_easy/aws/ec2/vpc.py
pulumi_easy/aws/iam/__init__.py
pulumi_easy/aws/iam/iam.py
pulumi_easy/aws/iam/s3.py
pulumi_easy/utils/__init__.py
pulumi_easy/utils/ip.py
pulumi_easy-0.21.0.dist-info/licenses/LICENSE
pulumi_easy-0.21.0.dist-info/METADATA
pulumi_easy-0.21.0.dist-info/WHEEL
pulumi_easy-0.21.0.dist-info/top_level.txt
pulumi_easy-0.21.0.dist-info/RECORD
