Metadata-Version: 2.4
Name: pulumi-easy
Version: 0.21.0
Summary: Add your description here
Author: Juni Yadi
Author-email: Juni Yadi <me@juniyadi.id>
License: MIT License
Keywords: pulumi,aws,infrastructure-as-code
Classifier: Development Status :: 4 - Beta
Classifier: Programming Language :: Python :: 3
Classifier: License :: OSI Approved :: MIT License
Classifier: Operating System :: OS Independent
Requires-Python: >=3.12
License-File: LICENSE
Provides-Extra: dev
Requires-Dist: pulumi<4.0.0,>=3.0.0; extra == "dev"
Requires-Dist: pulumi-aws<7.0.0,>=6.0.2; extra == "dev"
Requires-Dist: requests>=2.32.3; extra == "dev"
Dynamic: license-file
